hplot/__init__.py
hplot/base.py
hplot/config.py
hplot/plot_box.py
hplot/plot_heatmap.py
hplot/plot_legend.py
hplot/plot_plt.py
hplot/plot_sns.py
hplot/utils.py
hplot-0.1.1.dist-info/LICENSE
hplot-0.1.1.dist-info/METADATA
hplot-0.1.1.dist-info/WHEEL
hplot-0.1.1.dist-info/top_level.txt
hplot-0.1.1.dist-info/RECORD
