Metadata-Version: 2.1
Name: hplot
Version: 0.1.1
Summary: Some plot utils for research
Author: AeroH
Author-email: zhang.yuh@outlook.com
Requires-Python: >=3.8
License-File: LICENSE
Requires-Dist: numpy ==1.25.0
Requires-Dist: pytest ==7.4.0
Requires-Dist: pytest-cov ==4.1.0
Requires-Dist: matplotlib ==3.7.2
Requires-Dist: pandas ==2.0.3
Requires-Dist: scipy ==1.11.1
Requires-Dist: seaborn ==0.12.2
Requires-Dist: wrapt ==1.14.1
Requires-Dist: tabulate ==0.9.0
Requires-Dist: psutil ==5.9.1
Requires-Dist: tqdm
